{ "frames": {
   "Spaceman.aseprite": {
    "frame": { "x": 0, "y": 0, "w": 32, "h": 32 },
    "rotated": false,
    "trimmed": false,
    "spriteSourceSize": { "x": 0, "y": 0, "w": 32, "h": 32 },
    "sourceSize": { "w": 32, "h": 32 },
    "duration": 100
   }
 },
 "meta": {
  "app": "http://www.aseprite.org/",
  "version": "1.2.10-beta2-x64",
  "image": "/home/tommy/dev/Spritely/Spritely/Content/Sprites/Characters/Spaceman/Spaceman.png",
  "format": "I8",
  "size": { "w": 32, "h": 32 },
  "scale": "1",
  "frameTags": [
   { "name": "idle", "from": 0, "to": 0, "direction": "forward" }
  ],
  "layers": [
   { "name": "legs", "opacity": 255, "blendMode": "normal" },
   { "name": "pack", "opacity": 255, "blendMode": "normal" },
   { "name": "rear_arm", "opacity": 255, "blendMode": "normal" },
   { "name": "body", "opacity": 255, "blendMode": "normal" },
   { "name": "front_arm", "opacity": 255, "blendMode": "normal" },
   { "name": "head", "opacity": 255, "blendMode": "normal" }
  ],
  "slices": [
  ]
 }
}
